autopwlf/__init__.py
autopwlf/autopwlf.py
autopwlf-0.9.0.dist-info/LICENSE
autopwlf-0.9.0.dist-info/METADATA
autopwlf-0.9.0.dist-info/WHEEL
autopwlf-0.9.0.dist-info/top_level.txt
autopwlf-0.9.0.dist-info/RECORD
