Metadata-Version: 2.1
Name: autopwlf
Version: 0.9.0
Summary: Automated piecewise linear fitting
Home-page: https://github.com/nweerasuriya/auto_pwlf
Author: Nedeesha Weerasuriya
Author-email: nedeeshawork@gmail.com
License: MIT
Project-URL: GitHub, https://github.com/nweerasuriya/auto_pwlf
Classifier: Development Status :: 3 - Alpha
Classifier: Intended Audience :: Developers
Classifier: Natural Language :: English
Classifier: Operating System :: OS Independent
Classifier: Programming Language :: Python :: 3
Classifier: Programming Language :: Python :: 3.7
Classifier: Programming Language :: Python :: 3.8
Classifier: Programming Language :: Python :: 3.9
Classifier: License :: OSI Approved :: MIT License
Requires-Python: >=3.7
License-File: LICENSE
Requires-Dist: numpy>=1.24.0
Requires-Dist: scipy>=1.11.4
Requires-Dist: pwlf>=2.2.1
Requires-Dist: scikit-learn>=1.3.0
Provides-Extra: docs
Requires-Dist: sphinx>=3.0; extra == "docs"
Requires-Dist: sphinx-rtd-theme; extra == "docs"
